blockchainetl/__init__.py
blockchainetl/atomic_counter.py
blockchainetl/csv_utils.py
blockchainetl/exporters.py
blockchainetl/file_utils.py
blockchainetl/logging_utils.py
blockchainetl/jobs/__init__.py
blockchainetl/jobs/base_job.py
blockchainetl/jobs/exporters/__init__.py
blockchainetl/jobs/exporters/composite_item_exporter.py
blockchainetl/jobs/exporters/console_item_exporter.py
blockchainetl/jobs/exporters/gcs_item_exporter.py
blockchainetl/jobs/exporters/google_pubsub_item_exporter.py
blockchainetl/jobs/exporters/in_memory_item_exporter.py
blockchainetl/jobs/exporters/kafka_exporter.py
blockchainetl/jobs/exporters/kinesis_item_exporter.py
blockchainetl/jobs/exporters/multi_item_exporter.py
blockchainetl/jobs/exporters/postgres_item_exporter.py
blockchainetl/jobs/exporters/converters/__init__.py
blockchainetl/jobs/exporters/converters/composite_item_converter.py
blockchainetl/jobs/exporters/converters/int_to_decimal_item_converter.py
blockchainetl/jobs/exporters/converters/int_to_string_item_converter.py
blockchainetl/jobs/exporters/converters/list_field_item_converter.py
blockchainetl/jobs/exporters/converters/simple_item_converter.py
blockchainetl/jobs/exporters/converters/unix_timestamp_item_converter.py
blockchainetl/streaming/__init__.py
blockchainetl/streaming/postgres_utils.py
blockchainetl/streaming/streamer.py
blockchainetl/streaming/streamer_adapter_stub.py
blockchainetl/streaming/streaming_utils.py
tests/ethereumetl/__init__.py
tests/ethereumetl/test_progress_logger.py
tests/ethereumetl/job/__init__.py
tests/ethereumetl/job/helpers.py
tests/ethereumetl/job/mock_batch_web3_provider.py
tests/ethereumetl/job/mock_ipfs_client.py
tests/ethereumetl/job/mock_web3_provider.py
tests/ethereumetl/job/test_export_blocks_job.py
tests/ethereumetl/job/test_export_contracts_job.py
tests/ethereumetl/job/test_export_geth_traces_job.py
tests/ethereumetl/job/test_export_origin_job.py
tests/ethereumetl/job/test_export_receipts_job.py
xdcetl-1.0.1.dist-info/LICENSE
xdcetl-1.0.1.dist-info/METADATA
xdcetl-1.0.1.dist-info/WHEEL
xdcetl-1.0.1.dist-info/entry_points.txt
xdcetl-1.0.1.dist-info/top_level.txt
xdcetl-1.0.1.dist-info/RECORD
